flatsplode/__init__.py
flatsplode/__main__.py
flatsplode/flatsplode.py
flatsplode/utils.py
flatsplode-1.0.0.dist-info/entry_points.txt
flatsplode-1.0.0.dist-info/licenses/LICENSE
flatsplode-1.0.0.dist-info/WHEEL
flatsplode-1.0.0.dist-info/METADATA
flatsplode-1.0.0.dist-info/RECORD
